{
  "index": "eldritch-knight-18-improved-war-magic",
  "name": "Improved War Magic",
  "level": 18,
  "class": {
    "index": "fighter",
    "name": "Fighter",
    "url": "/api/2024/classes/fighter"
  },
  "subclass": {
    "index": "eldritch-knight",
    "name": "Eldritch Knight",
    "url": "/api/2024/subclasses/eldritch-knight"
  },
  "desc": [
    "When you take the Attack action on your turn, you can replace two of the attacks with a casting of one of your level 1 or level 2 Wizard spells that has a casting time of an action."
  ],
  "prerequisites": [],
  "url": "/api/2024/features/eldritch-knight-18-improved-war-magic"
}
